[
  {
    "ticker": "WPM",
    "name": "Wheaton Precious Metals Corp.",
    "sector": "Basic Materials",
    "price": 145.8,
    "avg_dividend_yield_5y": 0.00449,
    "dividends_per_share_ttm": 0,
    "market_cap_m": 66191.517924,
    "trailing_pe_ratio": 125.0926,
    "payout_ratio": 0
  },
  {
    "ticker": "BVN",
    "name": "=HYPERLINK(\"https://www.suredividend.com/sure-analysis-research-database/\",\"\")",
    "sector": "Basic Materials",
    "price": 38,
    "dividend_yield": 0.01,
    "avg_dividend_yield_5y": 0.00355,
    "dividends_per_share_ttm": 0
  },
  {
    "ticker": "PAAS",
    "name": "PAN AMERICAN SILVER CORP",
    "sector": "Basic Materials",
    "price": 57.8,
    "dividend_yield": 0.01,
    "avg_dividend_yield_5y": 0.00739,
    "dividends_per_share_ttm": 0,
    "market_cap_m": 21030.926954,
    "trailing_pe_ratio": 175.4039,
    "payout_ratio": 1.290151
  },
  {
    "ticker": "SSRM",
    "name": "SSR MINING INC.",
    "sector": "Basic Materials",
    "price": 28.1,
    "avg_dividend_yield_5y": 0.00629,
    "dividends_per_share_ttm": 0.28,
    "market_cap_m": 5706.362017,
    "trailing_pe_ratio": 25.9555,
    "payout_ratio": 0,
    "beta": 0.7864,
    "high_52w": 28.81,
    "low_52w": 8.65
  },
  {
    "ticker": "MAG",
    "name": "MAG SILVER CORP",
    "sector": "Basic Materials",
    "price": 24.55,
    "dividend_yield": 0.02,
    "avg_dividend_yield_5y": 0.00428,
    "dividends_per_share_ttm": 0.52,
    "market_cap_m": 2529.153009,
    "trailing_pe_ratio": 28.7878,
    "payout_ratio": 0,
    "beta": 1.1409
  },
  {
    "ticker": "CDE",
    "name": "Coeur Mining, Inc.",
    "sector": "Basic Materials",
    "price": 22.42,
    "avg_dividend_yield_5y": 0,
    "dividends_per_share_ttm": 1.5,
    "market_cap_m": 14398.52469,
    "trailing_pe_ratio": 35.2253,
    "payout_ratio": 0,
    "beta": 1.9848,
    "high_52w": 27.77,
    "low_52w": 4.58
  },
  {
    "ticker": "SVM",
    "name": "SILVERCORP METALS INC",
    "sector": "Basic Materials",
    "price": 10.97,
    "avg_dividend_yield_5y": 0.00228,
    "dividends_per_share_ttm": 0.03,
    "market_cap_m": 2390.744859,
    "trailing_pe_ratio": 26.9796,
    "payout_ratio": 0.203088,
    "beta": 1.2602,
    "high_52w": 14,
    "low_52w": 3.14
  },
  {
    "ticker": "FVI",
    "name": "FORTUNA MINING CORP.",
    "sector": "N/A",
    "price": 62.48,
    "avg_dividend_yield_5y": 0.01367,
    "dividends_per_share_ttm": 0.9,
    "beta": 0.7775,
    "high_52w": 63.06,
    "low_52w": 43.71
  },
  {
    "ticker": "HL",
    "name": "HECLA MINING CO/DE/",
    "sector": "Basic Materials",
    "price": 22.63,
    "avg_dividend_yield_5y": 0.00132,
    "dividends_per_share_ttm": 0.02,
    "market_cap_m": 15185.7988,
    "trailing_pe_ratio": 76.4354,
    "payout_ratio": 0.081897,
    "beta": 1.4358,
    "high_52w": 34.17,
    "low_52w": 4.45
  },
  {
    "ticker": "SEA",
    "name": "U.S. Global Sea to Sky Cargo ETF",
    "sector": "N/A",
    "price": 16.16,
    "avg_dividend_yield_5y": 0.09411,
    "dividends_per_share_ttm": 0.96,
    "beta": 0.7212,
    "high_52w": 16.53,
    "low_52w": 9.45
  },
  {
    "ticker": "NGD",
    "name": "New Gold Inc. /FI",
    "sector": "Basic Materials",
    "price": 11.09,
    "dividends_per_share_ttm": 0,
    "market_cap_m": 8747.691042,
    "trailing_pe_ratio": 85.2601,
    "payout_ratio": 0,
    "high_52w": 13.63,
    "low_52w": 2.6
  },
  {
    "ticker": "MUX",
    "name": "McEwen Mining Inc.",
    "sector": "Basic Materials",
    "price": 25.65,
    "dividends_per_share_ttm": 0,
    "market_cap_m": 1400.692549,
    "payout_ratio": 0,
    "high_52w": 29.7,
    "low_52w": 6.38
  },
  {
    "ticker": "GORO",
    "name": "GOLD RESOURCE CORP",
    "sector": "Basic Materials",
    "price": 1.65,
    "avg_dividend_yield_5y": 0.01044,
    "dividends_per_share_ttm": 0,
    "market_cap_m": 271.766351,
    "payout_ratio": 0
  },
  {
    "ticker": "TSG",
    "name": "Tristar Gold Inc.",
    "sector": "Consumer Cyclical",
    "price": 0.31,
    "dividends_per_share_ttm": 0,
    "market_cap_m": 5620.539733,
    "trailing_pe_ratio": 92.2883
  },
  {
    "ticker": "AUMN",
    "name": "Golden Minerals Co",
    "sector": "Basic Materials",
    "price": 0.28,
    "avg_dividend_yield_5y": 0,
    "dividends_per_share_ttm": 0,
    "payout_ratio": 0,
    "beta": -0.2493,
    "high_52w": 0.57,
    "low_52w": 0.08
  },
  {
    "ticker": "AG",
    "name": "FIRST MAJESTIC SILVER CORP",
    "sector": "Basic Materials",
    "price": 22.88,
    "avg_dividend_yield_5y": 0.00093,
    "dividends_per_share_ttm": 0,
    "market_cap_m": 6931.927944
  }
]